.class public test
.super java/lang/Object

.field private static in Ljava/util/Scanner;

.method static <clinit>()V
.limit stack 3
.limit locals 0
new java/util/Scanner
dup
getstatic java/lang/System/in Ljava/io/InputStream;
invokenonvirtual java/util/Scanner/<init>(Ljava/io/InputStream;)V
putstatic test/in Ljava/util/Scanner;
return
.end method

.method public static main([Ljava/lang/String;)V
.limit stack 100
.limit locals 8


.line 1
new java/util/Scanner
dup
getstatic java/lang/System.in Ljava/io/InputStream;
invokenonvirtual java/util/Scanner.<init>(Ljava/io/InputStream;)V
astore 1

.line 2
getstatic java/lang/System.out Ljava/io/PrintStream;
ldc "How much change? $"
invokevirtual java/io/PrintStream/print(Ljava/lang/String;)V

.line 4
aload 1
invokevirtual java/util/Scanner/nextDouble()D
ldc 100
i2d
dmul
invokestatic java/lang/Math/rint(D)D
d2i
istore 2

.line 5
getstatic java/lang/System.out Ljava/io/PrintStream;
ldc "Change for $"
iload 2
i2d
ldc2_w 100.000000
ddiv
invokestatic java/lang/Double.toString(D)Ljava/lang/String;
invokevirtual java/lang/String.concat(Ljava/lang/String;)Ljava/lang/String;
ldc ":"
invokevirtual java/lang/String.concat(Ljava/lang/String;)Ljava/lang/String;
invokevirtual java/io/PrintStream/println(Ljava/lang/String;)V

.line 7
iload 2
i2d
ldc 100
i2d
ddiv
d2i
istore 3

.line 8
iload 2
i2d
ldc 100
i2d
drem
d2i
dup
istore 2
pop

.line 10
iload 2
i2d
ldc 25
i2d
ddiv
d2i
istore 4

.line 11
iload 2
i2d
ldc 25
i2d
drem
d2i
dup
istore 2
pop

.line 13
iload 2
i2d
ldc 10
i2d
ddiv
d2i
istore 5

.line 14
iload 2
i2d
ldc 10
i2d
drem
d2i
dup
istore 2
pop

.line 16
iload 2
i2d
ldc 5
i2d
ddiv
d2i
istore 6

.line 17
iload 2
i2d
ldc 5
i2d
drem
d2i
dup
istore 2
pop

.line 19
iload 2
istore 7

.line 21
getstatic java/lang/System.out Ljava/io/PrintStream;
ldc "\t"
iload 3
invokestatic java/lang/Integer.toString(I)Ljava/lang/String;
invokevirtual java/lang/String.concat(Ljava/lang/String;)Ljava/lang/String;
ldc " dollars"
invokevirtual java/lang/String.concat(Ljava/lang/String;)Ljava/lang/String;
invokevirtual java/io/PrintStream/println(Ljava/lang/String;)V

.line 22
getstatic java/lang/System.out Ljava/io/PrintStream;
ldc "\t"
iload 4
invokestatic java/lang/Integer.toString(I)Ljava/lang/String;
invokevirtual java/lang/String.concat(Ljava/lang/String;)Ljava/lang/String;
ldc " quarters"
invokevirtual java/lang/String.concat(Ljava/lang/String;)Ljava/lang/String;
invokevirtual java/io/PrintStream/println(Ljava/lang/String;)V

.line 23
getstatic java/lang/System.out Ljava/io/PrintStream;
ldc "\t"
iload 5
invokestatic java/lang/Integer.toString(I)Ljava/lang/String;
invokevirtual java/lang/String.concat(Ljava/lang/String;)Ljava/lang/String;
ldc " dimes"
invokevirtual java/lang/String.concat(Ljava/lang/String;)Ljava/lang/String;
invokevirtual java/io/PrintStream/println(Ljava/lang/String;)V

.line 24
getstatic java/lang/System.out Ljava/io/PrintStream;
ldc "\t"
iload 6
invokestatic java/lang/Integer.toString(I)Ljava/lang/String;
invokevirtual java/lang/String.concat(Ljava/lang/String;)Ljava/lang/String;
ldc " nickels"
invokevirtual java/lang/String.concat(Ljava/lang/String;)Ljava/lang/String;
invokevirtual java/io/PrintStream/println(Ljava/lang/String;)V

.line 25
getstatic java/lang/System.out Ljava/io/PrintStream;
ldc "\t"
iload 7
invokestatic java/lang/Integer.toString(I)Ljava/lang/String;
invokevirtual java/lang/String.concat(Ljava/lang/String;)Ljava/lang/String;
ldc " pennies"
invokevirtual java/lang/String.concat(Ljava/lang/String;)Ljava/lang/String;
invokevirtual java/io/PrintStream/println(Ljava/lang/String;)V
return
.end method
