.class public test
.super java/lang/Object

.method public <init>()V
.limit stack 10
.limit locals 1

aload_0
invokenonvirtual java/lang/Object/<init>()V
return
.end method

.method public main()V
.limit stack 100
.limit locals 2

.line 2
ldc 1
istore 1

.line 3
loop_start_0:
iload 1
ldc 10
if_icmplt trueCase_2
iconst_0
goto end_3
trueCase_2:
iconst_1
end_3:
ifeq loop_end_1

.line 4
iload 1
i2d
ldc 2
i2d
drem
d2i
ldc 0
if_icmpeq trueCase_6
iconst_0
goto end_7
trueCase_6:
iconst_1
end_7:
ifeq else_4

.line 5
getstatic java/lang/System/out Ljava/io/PrintStream;
iload 1
invokevirtual java/io/PrintStream/print(I)V
getstatic java/lang/System/out Ljava/io/PrintStream;
invokevirtual java/io/PrintStream/println()V
goto if_end_5
else_4:

.line 8
getstatic java/lang/System/out Ljava/io/PrintStream;
iload 1
ineg
invokevirtual java/io/PrintStream/print(I)V
getstatic java/lang/System/out Ljava/io/PrintStream;
invokevirtual java/io/PrintStream/println()V
if_end_5:

.line 10
iinc 1 1
iload 1
pop
goto loop_start_0
loop_end_1:

.line 13
loop_start_8:
iload 1
ldc 0
if_icmpgt trueCase_10
iconst_0
goto end_11
trueCase_10:
iconst_1
end_11:
ifeq loop_end_9

.line 14
getstatic java/lang/System/out Ljava/io/PrintStream;
iload 1
invokevirtual java/io/PrintStream/print(I)V
getstatic java/lang/System/out Ljava/io/PrintStream;
invokevirtual java/io/PrintStream/println()V

.line 15
iinc 1 -1
iload 1
pop
goto loop_start_8
loop_end_9:
return
.end method

.method public static main([Ljava/lang/String;)V
.limit stack 100
.limit locals 2
new test
dup
invokenonvirtual test/<init>()V
invokevirtual test/main()V
return
.end method

